Metadata-Version: 2.1
Name: newsmeta
Version: 1.0.2
Summary: A python module for parsing HTML into news components.
Home-page: https://github.com/8W9aG/newsmeta
Author: Will Sackfield
Author-email: will.sackfield@gmail.com
License: MIT
Keywords: article parser
Platform: UNKNOWN
Classifier: License :: OSI Approved :: MIT License
Classifier: Programming Language :: Python :: 3
License-File: LICENSE
